polya/__init__.py
polya/_src/__init__.py
polya/_src/graphs.py
polya/_src/polya.py
polyaenum-0.0.1.dist-info/METADATA
polyaenum-0.0.1.dist-info/WHEEL
polyaenum-0.0.1.dist-info/top_level.txt
polyaenum-0.0.1.dist-info/RECORD
