Metadata-Version: 2.1
Name: polyaenum
Version: 0.0.1
Summary: A python implementation of Polya's enumeration theory.
Home-page: https://github.com/killiansheriff/polya
Author: Killian Sheriff
Author-email: ksheriff@mit.edu
License: MIT
Requires-Dist: numpy
Requires-Dist: sympy
Requires-Dist: igraph
